LICENSE
MANIFEST.in
README.md
pytest.ini
requirements.txt
runtests.py
setup.cfg
setup.py
src/django_multinavigation.egg-info/PKG-INFO
src/django_multinavigation.egg-info/SOURCES.txt
src/django_multinavigation.egg-info/dependency_links.txt
src/django_multinavigation.egg-info/top_level.txt
src/multinavigation/__init__.py
src/multinavigation/conf.py
src/multinavigation/examples/bootstrap_templates/multinavigation/breadcrumbs.html
src/multinavigation/examples/bootstrap_templates/multinavigation/flatnavigation.html
src/multinavigation/examples/bootstrap_templates/multinavigation/subnavigation.html
src/multinavigation/examples/bootstrap_templates/multinavigation/tabnavigation.html
src/multinavigation/examples/simple_templates/multinavigation/_tabnav_item.html
src/multinavigation/examples/simple_templates/multinavigation/_tabnav_item_dropdown.html
src/multinavigation/examples/simple_templates/multinavigation/_tabnav_nodes.html
src/multinavigation/examples/simple_templates/multinavigation/breadcrumbs.html
src/multinavigation/examples/simple_templates/multinavigation/flatnavigation.html
src/multinavigation/examples/simple_templates/multinavigation/subnavigation.html
src/multinavigation/examples/simple_templates/multinavigation/tabnavigation.html
src/multinavigation/templatetags/__init__.py
src/multinavigation/templatetags/multinavigation.py
src/multinavigation/templatetags/test_deep_nested.py
src/multinavigation/templatetags/test_simple_and_kwargs.py
src/multinavigation/templatetags/__pycache__/__init__.cpython-36.pyc
src/multinavigation/templatetags/__pycache__/__init__.cpython-39.pyc
src/multinavigation/templatetags/__pycache__/multinavigation.cpython-36.pyc
src/multinavigation/templatetags/__pycache__/multinavigation.cpython-39.pyc
src/multinavigation/templatetags/__pycache__/test_deep_nested.cpython-36-pytest-5.3.5.pyc
src/multinavigation/templatetags/__pycache__/test_deep_nested.cpython-39.pyc
src/multinavigation/templatetags/__pycache__/test_simple_and_kwargs.cpython-36-pytest-5.3.5.pyc
src/multinavigation/templatetags/__pycache__/test_simple_and_kwargs.cpython-39.pyc
src/test_app/__init__.py
src/test_app/context_processors.py
src/test_app/test_settings.py
